yc_django_files/__init__.py
yc_django_files/admin.py
yc_django_files/apps.py
yc_django_files/models.py
yc_django_files/serializers.py
yc_django_files/settings.py
yc_django_files/tests.py
yc_django_files/urls.py
yc_django_files/utils.py
yc_django_files/views.py
yc_django_files/api/__init__.py
yc_django_files/api/file_curd.py
yc_django_files/api/rep_curd.py
yc_django_files/migrations/__init__.py
yc_django_files-0.0.1.dist-info/LICENSE
yc_django_files-0.0.1.dist-info/METADATA
yc_django_files-0.0.1.dist-info/WHEEL
yc_django_files-0.0.1.dist-info/top_level.txt
yc_django_files-0.0.1.dist-info/RECORD
