Metadata-Version: 2.1
Name: yc_django_files
Version: 0.0.1
Summary: Django工具集开发
Author: LiuFei
Author-email: liufei-love@foxmail.com
License: MIT
Classifier: License :: OSI Approved :: MIT License
Classifier: Programming Language :: Python :: 3.12
License-File: LICENSE
Requires-Dist: yc-django-utils >=0.0.4
Requires-Dist: django-simple-history >=3.7.0
